password_generator/__init__.py
password_generator/generator.py
tests/__init__.py
tests/test.py
strongpass-0.1.0.dist-info/METADATA
strongpass-0.1.0.dist-info/WHEEL
strongpass-0.1.0.dist-info/top_level.txt
strongpass-0.1.0.dist-info/RECORD
