Metadata-Version: 2.4
Name: strongpass
Version: 0.1.0
Summary: A secure and flexible password generator with customizable options.
Home-page: https://github.com/yourusername/password_generator
Author: Hemal Pandya
Author-email: your-email@example.com
Classifier: Programming Language :: Python :: 3
Classifier: License :: OSI Approved :: MIT License
Classifier: Operating System :: OS Independent
Requires-Python: >=3.13
Dynamic: author
Dynamic: author-email
Dynamic: classifier
Dynamic: description
Dynamic: description-content-type
Dynamic: home-page
Dynamic: requires-python
Dynamic: summary
